<?xml version="1.0" encoding="UTF-8"?>
<settings xmlns="http://maven.apache.org/SETTINGS/1.0.0"
          xmlns:xsi="http://www.w3.org/2001/XMLSchema-instance"
          xsi:schemaLocation="http://maven.apache.org/SETTINGS/1.0.0 http://maven.apache.org/xsd/settings-1.0.0.xsd">
    <mirrors>
        <mirror>
            <id>nexus-aliyun</id>
            <mirrorOf>central</mirrorOf>
            <name>Nexus aliyun</name>
            <url>https://maven.aliyun.com/nexus/content/groups/public/</url>
        </mirror>
        <mirror>
            <id>maven-default-http-blocker</id>
            <mirrorOf>external:dummy:*</mirrorOf>
            <name>Pseudo repository to mirror external repositories initially using HTTP.</name>
            <url>http://0.0.0.0/</url>
        </mirror>
    </mirrors>
    <profiles>
        <profile>
            <id>wxgx</id>
            <repositories>
                <repository>
                    <id>wxgx</id>
                    <url>http://10.15.98.52:8081/repository/maven-public/</url>
                </repository>
            </repositories>
        </profile>
    </profiles>
</settings>